ifood/__init__.py
ifood-0.0.2.dist-info/LICENSE
ifood-0.0.2.dist-info/METADATA
ifood-0.0.2.dist-info/WHEEL
ifood-0.0.2.dist-info/top_level.txt
ifood-0.0.2.dist-info/RECORD
