Metadata-Version: 2.1
Name: ifood
Version: 0.0.2
Summary: Extract data from ifood products
Home-page: https://github.com/claudiotorresarbe/ifood
Author: Claudio Torres Arbe
Author-email: claudiotarbe@gmail.com
License: UNKNOWN
Platform: UNKNOWN
Classifier: Programming Language :: Python :: 3.8
Classifier: License :: OSI Approved :: MIT License
Classifier: Operating System :: OS Independent
Requires-Python: >=3.6
Requires-Dist: requests (<=2.21.0)
